yxd/__init__.py
yxd/__main__.py
yxd/arguments.py
yxd/config.py
yxd/downloader.py
yxd/exceptions.py
yxd/extractor.py
yxd/html_archiver.py
yxd/logger.py
yxd/mylogger.py
yxd/myutil.py
yxd/progressbar.py
yxd/settings.py
yxd/settings.reference.json.py
yxd/settings2.py
yxd/singleton.py
yxd/videoinfo2.py
yxd/webshare_quota.py
yxd/youtube/__init__.py
yxd/youtube/api.py
yxd/youtube/channel.py
yxd/youtube/comments.py
yxd/youtube/local_playlist.py
yxd/youtube/playlist.py
yxd/youtube/proto.py
yxd/youtube/proto_debug.py
yxd/youtube/search.py
yxd/youtube/subscriptions.py
yxd/youtube/util.py
yxd/youtube/watch.py
yxd/youtube/yt_data_extract/__init__.py
yxd/youtube/yt_data_extract/common.py
yxd/youtube/yt_data_extract/everything_else.py
yxd/youtube/yt_data_extract/watch_extraction.py
yxd2-1.0.4.dist-info/licenses/LICENSE
yxd2-1.0.4.dist-info/METADATA
yxd2-1.0.4.dist-info/WHEEL
yxd2-1.0.4.dist-info/entry_points.txt
yxd2-1.0.4.dist-info/top_level.txt
yxd2-1.0.4.dist-info/RECORD
