Metadata-Version: 2.4
Name: yxd2
Version: 1.0.4
Summary: A Python tool for downloading YouTube XML data and transcripts
Author-email: vb <i@s.biz>
License:                     GNU AFFERO GENERAL PUBLIC LICENSE
Project-URL: Homepage, http://example.com
Classifier: Development Status :: 5 - Production/Stable
Classifier: Intended Audience :: Developers
Classifier: License :: OSI Approved :: GNU Affero General Public License v3
Classifier: Programming Language :: Python :: 3
Classifier: Programming Language :: Python :: 3.8
Classifier: Programming Language :: Python :: 3.9
Classifier: Programming Language :: Python :: 3.10
Classifier: Programming Language :: Python :: 3.11
Classifier: Programming Language :: Python :: 3.12
Requires-Python: >=3.8
License-File: LICENSE
Requires-Dist: Brotli
Requires-Dist: cachetools
Requires-Dist: defusedxml
Requires-Dist: emoji
Requires-Dist: Flask
Requires-Dist: gevent
Requires-Dist: PySocks
Requires-Dist: requests
Requires-Dist: stem
Requires-Dist: urllib3
Requires-Dist: youtube-transcript-api
Dynamic: license-file
